org	PACKAGE_IDENTIFIER	false
apache	PACKAGE_IDENTIFIER	false
xalan	PACKAGE_IDENTIFIER	false
xsltc	PACKAGE_IDENTIFIER	false
compiler	PACKAGE_IDENTIFIER	false
org	PACKAGE_IDENTIFIER	false
apache	PACKAGE_IDENTIFIER	false
bcel	PACKAGE_IDENTIFIER	false
generic	PACKAGE_IDENTIFIER	false
ConstantPoolGen	TYPE_IDENTIFIER	false
org	PACKAGE_IDENTIFIER	false
apache	PACKAGE_IDENTIFIER	false
bcel	PACKAGE_IDENTIFIER	false
generic	PACKAGE_IDENTIFIER	false
INVOKEINTERFACE	TYPE_IDENTIFIER	false
org	PACKAGE_IDENTIFIER	false
apache	PACKAGE_IDENTIFIER	false
bcel	PACKAGE_IDENTIFIER	false
generic	PACKAGE_IDENTIFIER	false
INVOKESPECIAL	TYPE_IDENTIFIER	false
org	PACKAGE_IDENTIFIER	false
apache	PACKAGE_IDENTIFIER	false
bcel	PACKAGE_IDENTIFIER	false
generic	PACKAGE_IDENTIFIER	false
INVOKEVIRTUAL	TYPE_IDENTIFIER	false
org	PACKAGE_IDENTIFIER	false
apache	PACKAGE_IDENTIFIER	false
bcel	PACKAGE_IDENTIFIER	false
generic	PACKAGE_IDENTIFIER	false
InstructionList	TYPE_IDENTIFIER	false
org	PACKAGE_IDENTIFIER	false
apache	PACKAGE_IDENTIFIER	false
bcel	PACKAGE_IDENTIFIER	false
generic	PACKAGE_IDENTIFIER	false
NEW	TYPE_IDENTIFIER	false
org	PACKAGE_IDENTIFIER	false
apache	PACKAGE_IDENTIFIER	false
bcel	PACKAGE_IDENTIFIER	false
generic	PACKAGE_IDENTIFIER	false
PUSH	TYPE_IDENTIFIER	false
org	PACKAGE_IDENTIFIER	false
apache	PACKAGE_IDENTIFIER	false
xalan	PACKAGE_IDENTIFIER	false
xsltc	PACKAGE_IDENTIFIER	false
compiler	PACKAGE_IDENTIFIER	false
util	PACKAGE_IDENTIFIER	false
ClassGenerator	TYPE_IDENTIFIER	false
org	PACKAGE_IDENTIFIER	false
apache	PACKAGE_IDENTIFIER	false
xalan	PACKAGE_IDENTIFIER	false
xsltc	PACKAGE_IDENTIFIER	false
compiler	PACKAGE_IDENTIFIER	false
util	PACKAGE_IDENTIFIER	false
MethodGenerator	TYPE_IDENTIFIER	false
org	PACKAGE_IDENTIFIER	false
apache	PACKAGE_IDENTIFIER	false
xalan	PACKAGE_IDENTIFIER	false
xsltc	PACKAGE_IDENTIFIER	false
compiler	PACKAGE_IDENTIFIER	false
util	PACKAGE_IDENTIFIER	false
Type	TYPE_IDENTIFIER	false
org	PACKAGE_IDENTIFIER	false
apache	PACKAGE_IDENTIFIER	false
xalan	PACKAGE_IDENTIFIER	false
xsltc	PACKAGE_IDENTIFIER	false
compiler	PACKAGE_IDENTIFIER	false
util	PACKAGE_IDENTIFIER	false
TypeCheckError	TYPE_IDENTIFIER	false
Message	TYPE_IDENTIFIER	true
Instruction	TYPE_IDENTIFIER	false
_terminate	VARIABLE_IDENTIFIER	true
parseContents	METHOD_IDENTIFIER	true
Parser	TYPE_IDENTIFIER	false
parser	VARIABLE_IDENTIFIER	true
String	TYPE_IDENTIFIER	false
termstr	VARIABLE_IDENTIFIER	true
getAttribute	METHOD_IDENTIFIER	false
termstr	VARIABLE_IDENTIFIER	false
_terminate	VARIABLE_IDENTIFIER	false
termstr	VARIABLE_IDENTIFIER	false
equals	METHOD_IDENTIFIER	false
parseChildren	METHOD_IDENTIFIER	false
parser	VARIABLE_IDENTIFIER	false
Type	TYPE_IDENTIFIER	false
typeCheck	METHOD_IDENTIFIER	true
SymbolTable	TYPE_IDENTIFIER	false
stable	VARIABLE_IDENTIFIER	true
TypeCheckError	TYPE_IDENTIFIER	false
typeCheckContents	METHOD_IDENTIFIER	false
stable	VARIABLE_IDENTIFIER	false
Type	TYPE_IDENTIFIER	false
Void	VARIABLE_IDENTIFIER	false
translate	METHOD_IDENTIFIER	true
ClassGenerator	TYPE_IDENTIFIER	false
classGen	VARIABLE_IDENTIFIER	true
MethodGenerator	TYPE_IDENTIFIER	false
methodGen	VARIABLE_IDENTIFIER	true
ConstantPoolGen	TYPE_IDENTIFIER	false
cpg	VARIABLE_IDENTIFIER	true
classGen	VARIABLE_IDENTIFIER	false
getConstantPool	METHOD_IDENTIFIER	false
InstructionList	TYPE_IDENTIFIER	false
il	VARIABLE_IDENTIFIER	true
methodGen	VARIABLE_IDENTIFIER	false
getInstructionList	METHOD_IDENTIFIER	false
il	VARIABLE_IDENTIFIER	false
append	METHOD_IDENTIFIER	false
classGen	VARIABLE_IDENTIFIER	false
loadTranslet	METHOD_IDENTIFIER	false
elementCount	METHOD_IDENTIFIER	false
il	VARIABLE_IDENTIFIER	false
append	METHOD_IDENTIFIER	false
PUSH	TYPE_IDENTIFIER	false
cpg	VARIABLE_IDENTIFIER	false
SyntaxTreeNode	TYPE_IDENTIFIER	false
child	VARIABLE_IDENTIFIER	true
SyntaxTreeNode	TYPE_IDENTIFIER	false
elementAt	METHOD_IDENTIFIER	false
child	VARIABLE_IDENTIFIER	false
Text	TYPE_IDENTIFIER	false
il	VARIABLE_IDENTIFIER	false
append	METHOD_IDENTIFIER	false
PUSH	TYPE_IDENTIFIER	false
cpg	VARIABLE_IDENTIFIER	false
Text	TYPE_IDENTIFIER	false
child	VARIABLE_IDENTIFIER	false
getText	METHOD_IDENTIFIER	false
il	VARIABLE_IDENTIFIER	false
append	METHOD_IDENTIFIER	false
methodGen	VARIABLE_IDENTIFIER	false
loadHandler	METHOD_IDENTIFIER	false
il	VARIABLE_IDENTIFIER	false
append	METHOD_IDENTIFIER	false
NEW	TYPE_IDENTIFIER	false
cpg	VARIABLE_IDENTIFIER	false
addClass	METHOD_IDENTIFIER	false
STREAM_XML_OUTPUT	VARIABLE_IDENTIFIER	false
il	VARIABLE_IDENTIFIER	false
append	METHOD_IDENTIFIER	false
methodGen	VARIABLE_IDENTIFIER	false
storeHandler	METHOD_IDENTIFIER	false
il	VARIABLE_IDENTIFIER	false
append	METHOD_IDENTIFIER	false
NEW	TYPE_IDENTIFIER	false
cpg	VARIABLE_IDENTIFIER	false
addClass	METHOD_IDENTIFIER	false
STRING_WRITER	VARIABLE_IDENTIFIER	false
il	VARIABLE_IDENTIFIER	false
append	METHOD_IDENTIFIER	false
DUP	VARIABLE_IDENTIFIER	false
il	VARIABLE_IDENTIFIER	false
append	METHOD_IDENTIFIER	false
DUP	VARIABLE_IDENTIFIER	false
il	VARIABLE_IDENTIFIER	false
append	METHOD_IDENTIFIER	false
INVOKESPECIAL	TYPE_IDENTIFIER	false
cpg	VARIABLE_IDENTIFIER	false
addMethodref	METHOD_IDENTIFIER	false
STRING_WRITER	VARIABLE_IDENTIFIER	false
il	VARIABLE_IDENTIFIER	false
append	METHOD_IDENTIFIER	false
methodGen	VARIABLE_IDENTIFIER	false
loadHandler	METHOD_IDENTIFIER	false
il	VARIABLE_IDENTIFIER	false
append	METHOD_IDENTIFIER	false
INVOKESPECIAL	TYPE_IDENTIFIER	false
cpg	VARIABLE_IDENTIFIER	false
addMethodref	METHOD_IDENTIFIER	false
STREAM_XML_OUTPUT	VARIABLE_IDENTIFIER	false
il	VARIABLE_IDENTIFIER	false
append	METHOD_IDENTIFIER	false
methodGen	VARIABLE_IDENTIFIER	false
loadHandler	METHOD_IDENTIFIER	false
il	VARIABLE_IDENTIFIER	false
append	METHOD_IDENTIFIER	false
SWAP	VARIABLE_IDENTIFIER	false
il	VARIABLE_IDENTIFIER	false
append	METHOD_IDENTIFIER	false
INVOKEINTERFACE	TYPE_IDENTIFIER	false
cpg	VARIABLE_IDENTIFIER	false
addInterfaceMethodref	METHOD_IDENTIFIER	false
TRANSLET_OUTPUT_INTERFACE	VARIABLE_IDENTIFIER	false
WRITER_SIG	VARIABLE_IDENTIFIER	false
il	VARIABLE_IDENTIFIER	false
append	METHOD_IDENTIFIER	false
methodGen	VARIABLE_IDENTIFIER	false
loadHandler	METHOD_IDENTIFIER	false
il	VARIABLE_IDENTIFIER	false
append	METHOD_IDENTIFIER	false
PUSH	TYPE_IDENTIFIER	false
cpg	VARIABLE_IDENTIFIER	false
il	VARIABLE_IDENTIFIER	false
append	METHOD_IDENTIFIER	false
INVOKEINTERFACE	TYPE_IDENTIFIER	false
cpg	VARIABLE_IDENTIFIER	false
addInterfaceMethodref	METHOD_IDENTIFIER	false
TRANSLET_OUTPUT_INTERFACE	VARIABLE_IDENTIFIER	false
STRING_SIG	VARIABLE_IDENTIFIER	false
il	VARIABLE_IDENTIFIER	false
append	METHOD_IDENTIFIER	false
methodGen	VARIABLE_IDENTIFIER	false
loadHandler	METHOD_IDENTIFIER	false
il	VARIABLE_IDENTIFIER	false
append	METHOD_IDENTIFIER	false
ICONST_1	VARIABLE_IDENTIFIER	false
il	VARIABLE_IDENTIFIER	false
append	METHOD_IDENTIFIER	false
INVOKEINTERFACE	TYPE_IDENTIFIER	false
cpg	VARIABLE_IDENTIFIER	false
addInterfaceMethodref	METHOD_IDENTIFIER	false
TRANSLET_OUTPUT_INTERFACE	VARIABLE_IDENTIFIER	false
il	VARIABLE_IDENTIFIER	false
append	METHOD_IDENTIFIER	false
methodGen	VARIABLE_IDENTIFIER	false
loadHandler	METHOD_IDENTIFIER	false
il	VARIABLE_IDENTIFIER	false
append	METHOD_IDENTIFIER	false
INVOKEINTERFACE	TYPE_IDENTIFIER	false
cpg	VARIABLE_IDENTIFIER	false
addInterfaceMethodref	METHOD_IDENTIFIER	false
TRANSLET_OUTPUT_INTERFACE	VARIABLE_IDENTIFIER	false
translateContents	METHOD_IDENTIFIER	false
classGen	VARIABLE_IDENTIFIER	false
methodGen	VARIABLE_IDENTIFIER	false
il	VARIABLE_IDENTIFIER	false
append	METHOD_IDENTIFIER	false
methodGen	VARIABLE_IDENTIFIER	false
loadHandler	METHOD_IDENTIFIER	false
il	VARIABLE_IDENTIFIER	false
append	METHOD_IDENTIFIER	false
INVOKEINTERFACE	TYPE_IDENTIFIER	false
cpg	VARIABLE_IDENTIFIER	false
addInterfaceMethodref	METHOD_IDENTIFIER	false
TRANSLET_OUTPUT_INTERFACE	VARIABLE_IDENTIFIER	false
il	VARIABLE_IDENTIFIER	false
append	METHOD_IDENTIFIER	false
INVOKEVIRTUAL	TYPE_IDENTIFIER	false
cpg	VARIABLE_IDENTIFIER	false
addMethodref	METHOD_IDENTIFIER	false
STRING_WRITER	VARIABLE_IDENTIFIER	false
STRING_SIG	VARIABLE_IDENTIFIER	false
il	VARIABLE_IDENTIFIER	false
append	METHOD_IDENTIFIER	false
SWAP	VARIABLE_IDENTIFIER	false
il	VARIABLE_IDENTIFIER	false
append	METHOD_IDENTIFIER	false
methodGen	VARIABLE_IDENTIFIER	false
storeHandler	METHOD_IDENTIFIER	false
il	VARIABLE_IDENTIFIER	false
append	METHOD_IDENTIFIER	false
INVOKEVIRTUAL	TYPE_IDENTIFIER	false
cpg	VARIABLE_IDENTIFIER	false
addMethodref	METHOD_IDENTIFIER	false
TRANSLET_CLASS	VARIABLE_IDENTIFIER	false
STRING_SIG	VARIABLE_IDENTIFIER	false
_terminate	VARIABLE_IDENTIFIER	false
einit	VARIABLE_IDENTIFIER	true
cpg	VARIABLE_IDENTIFIER	false
addMethodref	METHOD_IDENTIFIER	false
il	VARIABLE_IDENTIFIER	false
append	METHOD_IDENTIFIER	false
NEW	TYPE_IDENTIFIER	false
cpg	VARIABLE_IDENTIFIER	false
addClass	METHOD_IDENTIFIER	false
il	VARIABLE_IDENTIFIER	false
append	METHOD_IDENTIFIER	false
DUP	VARIABLE_IDENTIFIER	false
il	VARIABLE_IDENTIFIER	false
append	METHOD_IDENTIFIER	false
PUSH	TYPE_IDENTIFIER	false
cpg	VARIABLE_IDENTIFIER	false
il	VARIABLE_IDENTIFIER	false
append	METHOD_IDENTIFIER	false
INVOKESPECIAL	TYPE_IDENTIFIER	false
einit	VARIABLE_IDENTIFIER	false
il	VARIABLE_IDENTIFIER	false
append	METHOD_IDENTIFIER	false
ATHROW	VARIABLE_IDENTIFIER	false
